simplivity/__init__.py
simplivity/connection.py
simplivity/exceptions.py
simplivity/ovc_client.py
simplivity/resources/__init__.py
simplivity/resources/backups.py
simplivity/resources/certificates.py
simplivity/resources/cluster_groups.py
simplivity/resources/datastores.py
simplivity/resources/external_stores.py
simplivity/resources/hosts.py
simplivity/resources/omnistack_clusters.py
simplivity/resources/policies.py
simplivity/resources/resource.py
simplivity/resources/tasks.py
simplivity/resources/virtual_machines.py
simplivity-1.1.1.dist-info/LICENSE
simplivity-1.1.1.dist-info/METADATA
simplivity-1.1.1.dist-info/WHEEL
simplivity-1.1.1.dist-info/top_level.txt
simplivity-1.1.1.dist-info/RECORD
