Metadata-Version: 2.1
Name: simplivity
Version: 1.1.1
Summary: HPE SimpliVity Python Library
Home-page: https://github.com/HewlettPackard/simplivity-python
Author: Hewlett Packard Enterprise Development LP
Author-email: simplivity-pythonsdk@hpe.com
License: Apache
Download-URL: https://github.com/HewlettPackard/simplivity-python/tarball/v1.1.1
Keywords: simplivity,hpe
Platform: UNKNOWN
Requires-Python: >=3.3
